netpwn/__init__.py
netpwn/__main__.py
netpwn/config.py
netpwn/services/ListenerService.py
netpwn/services/ParametersParserService.py
netpwn/services/TerminalService.py
netpwn/services/__init__.py
tests/__init__.py
tests/test_listenner_service.py
tests/test_parameters_parser_service.py
netpwn-1.4.post1.dist-info/LICENSE
netpwn-1.4.post1.dist-info/METADATA
netpwn-1.4.post1.dist-info/WHEEL
netpwn-1.4.post1.dist-info/entry_points.txt
netpwn-1.4.post1.dist-info/top_level.txt
netpwn-1.4.post1.dist-info/RECORD
