Metadata-Version: 2.1
Name: netpwn
Version: 1.4.post1
Summary: A netcat listener alternative with automatic shell stabilization.
Home-page: https://github.com/anthares101/netpwn
Author: Ángel Heredia
License: GPL-2.0
Project-URL: Release notes, https://github.com/anthares101/netpwn/releases
Keywords: windows macos linux shell reverse-shell tool hacking netcat tty pty cybersecurity reverse pwntools hacktoberfest kali
Platform: UNKNOWN
Requires-Python: >=3
Requires-Dist: pwntools
